Metadata-Version: 2.4
Name: django-pghistory
Version: 3.9.1
Summary: History tracking for Django and Postgres
License: BSD-3-Clause
License-File: LICENSE
Author: Wes Kendall
Requires-Python: >=3.10.0,<4
Classifier: Framework :: Django
Classifier: Framework :: Django :: 4.2
Classifier: Framework :: Django :: 5.0
Classifier: Framework :: Django :: 5.1
Classifier: Framework :: Django :: 5.2
Classifier: Framework :: Django :: 6.0
Classifier: Intended Audience :: Developers
Classifier: License :: OSI Approved :: BSD License
Classifier: Operating System :: OS Independent
Classifier: Programming Language :: Python
Classifier: Programming Language :: Python :: 3
Classifier: Programming Language :: Python :: 3.10
Classifier: Programming Language :: Python :: 3.11
Classifier: Programming Language :: Python :: 3.12
Classifier: Programming Language :: Python :: 3.13
Classifier: Programming Language :: Python :: 3.14
Classifier: Programming Language :: Python :: 3 :: Only
Requires-Dist: django (>=4.2)
Requires-Dist: django-pgtrigger (>=4.15.0)
Project-URL: Documentation, https://django-pghistory.readthedocs.io
Project-URL: Homepage, https://github.com/AmbitionEng/django-pghistory
Project-URL: Repository, https://github.com/AmbitionEng/django-pghistory
